alfworld/__init__.py
alfworld/info.py
alfworld/utils.py
alfworld/agents/__init__.py
alfworld/agents/agent/__init__.py
alfworld/agents/agent/base_agent.py
alfworld/agents/agent/text_dagger_agent.py
alfworld/agents/agent/text_dqn_agent.py
alfworld/agents/agent/vision_dagger_agent.py
alfworld/agents/config/rewards.json
alfworld/agents/controller/__init__.py
alfworld/agents/controller/base.py
alfworld/agents/controller/mrcnn.py
alfworld/agents/controller/mrcnn_astar.py
alfworld/agents/controller/oracle.py
alfworld/agents/controller/oracle_astar.py
alfworld/agents/detector/__init__.py
alfworld/agents/detector/coco_eval.py
alfworld/agents/detector/coco_utils.py
alfworld/agents/detector/engine.py
alfworld/agents/detector/group_by_aspect_ratio.py
alfworld/agents/detector/mrcnn.py
alfworld/agents/detector/train.py
alfworld/agents/detector/transforms.py
alfworld/agents/detector/utils.py
alfworld/agents/environment/__init__.py
alfworld/agents/environment/alfred_hybrid.py
alfworld/agents/environment/alfred_thor_env.py
alfworld/agents/environment/alfred_tw_env.py
alfworld/agents/eval/__init__.py
alfworld/agents/eval/evaluate_dagger.py
alfworld/agents/eval/evaluate_dqn.py
alfworld/agents/eval/evaluate_vision_dagger.py
alfworld/agents/expert/__init__.py
alfworld/agents/expert/handcoded_expert.py
alfworld/agents/expert/handcoded_expert_thor.py
alfworld/agents/expert/handcoded_expert_tw.py
alfworld/agents/modules/__init__.py
alfworld/agents/modules/generic.py
alfworld/agents/modules/layers.py
alfworld/agents/modules/memory.py
alfworld/agents/modules/model.py
alfworld/agents/modules/segment_tree.py
alfworld/agents/utils/__init__.py
alfworld/agents/utils/misc.py
alfworld/data/alfred.pddl
alfworld/data/alfred.twl2
alfworld/env/__init__.py
alfworld/env/reward.py
alfworld/env/tasks.py
alfworld/env/thor_env.py
alfworld/gen/__init__.py
alfworld/gen/constants.py
alfworld/gen/goal_library.py
alfworld/gen/agents/__init__.py
alfworld/gen/agents/agent_base.py
alfworld-0.4.1.dist-info/LICENSE
alfworld-0.4.1.dist-info/METADATA
alfworld-0.4.1.dist-info/WHEEL
alfworld-0.4.1.dist-info/top_level.txt
alfworld-0.4.1.dist-info/RECORD
