Metadata-Version: 2.1
Name: alfworld
Version: 0.4.1
Summary: ALFWorld - Aligning Text and Embodied Environments for Interactive Learning.
License: MIT License
License-File: LICENSE
Requires-Dist: textworld[pddl]>=1.6.1
Provides-Extra: full
Requires-Dist: ai2thor==2.1.0; extra == "full"
Requires-Dist: opencv-python; extra == "full"
Requires-Dist: pandas; extra == "full"
Requires-Dist: textworld[pddl]>=1.6.1; extra == "full"
Requires-Dist: torch; extra == "full"
Requires-Dist: torchvision; extra == "full"
Requires-Dist: tqdm; extra == "full"
Requires-Dist: werkzeug==2.0.3; extra == "full"
Requires-Dist: h5py; extra == "full"
Requires-Dist: pycocotools; extra == "full"
Requires-Dist: transformers; extra == "full"
Requires-Dist: visdom; extra == "full"
Provides-Extra: vis
Requires-Dist: ai2thor==2.1.0; extra == "vis"
Requires-Dist: opencv-python; extra == "vis"
Requires-Dist: pandas; extra == "vis"
Requires-Dist: torch; extra == "vis"
Requires-Dist: torchvision; extra == "vis"
Requires-Dist: tqdm; extra == "vis"
Requires-Dist: werkzeug==2.0.3; extra == "vis"
